[
    {
        "index": 69,
        "nama": "Virdian Dwi Cahyaningrum S.Pd",
        "keterangan": "Matematika",
        "kelas": "X-7",
        "hari": 3,
        "jam": 3
    },
    {
        "index": 69,
        "nama": "Virdian Dwi Cahyaningrum S.Pd",
        "keterangan": "Matematika",
        "kelas": "X-7",
        "hari": 3,
        "jam": 4
    },
    {
        "index": 69,
        "nama": "Virdian Dwi Cahyaningrum S.Pd",
        "keterangan": "Matematika",
        "kelas": "X-7",
        "hari": 5,
        "jam": 3
    },
    {
        "index": 69,
        "nama": "Virdian Dwi Cahyaningrum S.Pd",
        "keterangan": "Matematika",
        "kelas": "X-7",
        "hari": 5,
        "jam": 4
    },
    {
        "index": 69,
        "nama": "Virdian Dwi Cahyaningrum S.Pd",
        "keterangan": "Matematika",
        "kelas": "X-8",
        "hari": 1,
        "jam": 1
    },
    {
        "index": 69,
        "nama": "Virdian Dwi Cahyaningrum S.Pd",
        "keterangan": "Matematika",
        "kelas": "X-8",
        "hari": 1,
        "jam": 2
    },
    {
        "index": 69,
        "nama": "Virdian Dwi Cahyaningrum S.Pd",
        "keterangan": "Matematika",
        "kelas": "X-8",
        "hari": 4,
        "jam": 9
    },
    {
        "index": 69,
        "nama": "Virdian Dwi Cahyaningrum S.Pd",
        "keterangan": "Matematika",
        "kelas": "X-8",
        "hari": 4,
        "jam": 10
    },
    {
        "index": 69,
        "nama": "Virdian Dwi Cahyaningrum S.Pd",
        "keterangan": "Matematika",
        "kelas": "X-9",
        "hari": 3,
        "jam": 1
    },
    {
        "index": 69,
        "nama": "Virdian Dwi Cahyaningrum S.Pd",
        "keterangan": "Matematika",
        "kelas": "X-9",
        "hari": 3,
        "jam": 2
    },
    {
        "index": 69,
        "nama": "Virdian Dwi Cahyaningrum S.Pd",
        "keterangan": "Matematika",
        "kelas": "X-9",
        "hari": 5,
        "jam": 5
    },
    {
        "index": 69,
        "nama": "Virdian Dwi Cahyaningrum S.Pd",
        "keterangan": "Matematika",
        "kelas": "X-9",
        "hari": 5,
        "jam": 6
    }
]